mcpbytes_lambda/core/__init__.py
mcpbytes_lambda/core/adapter.py
mcpbytes_lambda/core/decorators.py
mcpbytes_lambda/core/exceptions.py
mcpbytes_lambda/core/protocol.py
mcpbytes_lambda/core/server.py
mcpbytes_lambda/core/types.py
mcpbytes_lambda/core/validation.py
mcpbytes_lambda_core-0.2.1.dist-info/METADATA
mcpbytes_lambda_core-0.2.1.dist-info/WHEEL
mcpbytes_lambda_core-0.2.1.dist-info/RECORD
