Metadata-Version: 2.4
Name: mcpbytes-lambda-core
Version: 0.2.1
Summary: Transport-agnostic Model Context Protocol (MCP) server core for AWS Lambda
Project-URL: Homepage, https://mcpbytes.com/
Project-URL: Repository, https://github.com/MCPBytes/mcpbytes-lambda
Project-URL: Issues, https://github.com/MCPBytes/mcpbytes-lambda/issues
Project-URL: Documentation, https://github.com/MCPBytes/mcpbytes-lambda#readme
Author-email: "MCPBytes.com" <hello@mcpbytes.com>
License-Expression: Apache-2.0
Keywords: ai,aws-lambda,core,mcp,model-context-protocol,serverless
Classifier: Development Status :: 4 - Beta
Classifier: Intended Audience :: Developers
Classifier: License :: OSI Approved :: Apache Software License
Classifier: Programming Language :: Python :: 3
Classifier: Programming Language :: Python :: 3.12
Classifier: Topic :: Internet :: WWW/HTTP :: HTTP Servers
Classifier: Topic :: Software Development :: Libraries :: Application Frameworks
Classifier: Topic :: Software Development :: Libraries :: Python Modules
Requires-Python: >=3.12
